doka/__init__.py
doka/commands/__init__.py
doka/commands/config.py
doka/commands/inspect.py
doka/commands/nginx.py
doka/commands/portainer.py
doka/commands/project.py
doka/commands/stack.py
doka/commands/unit.py
doka/config.py
doka/kernel/__init__.py
doka/kernel/actions/__init__.py
doka/kernel/actions/stack.py
doka/kernel/actions/unit.py
doka/kernel/definition/__init__.py
doka/kernel/definition/entities.py
doka/kernel/repository/__init__.py
doka/kernel/repository/exceptions.py
doka/kernel/repository/filters.py
doka/kernel/repository/repositories.py
doka/kernel/services/__init__.py
doka/kernel/services/docker.py
doka/kernel/services/git.py
doka/kernel/services/tester.py
doka/kernel/storage/__init__.py
doka/kernel/storage/code.py
doka/kernel/storage/env.py
doka/kernel/storage/hooks.py
doka/kernel/storage/json.py
doka/kernel/storage/yaml.py
doka/plugins/__init__.py
doka/plugins/nginx/Dockerfile
doka/plugins/nginx/__init__.py
doka/plugins/nginx/conf/nginx.conf
doka/plugins/nginx/nginx.py
doka/plugins/nginx/templates/http_server.txt
doka/plugins/nginx/templates/nginx.txt
doka/tests/scale_test.py
doka-0.4.9.dist-info/entry_points.txt
doka-0.4.9.dist-info/WHEEL
doka-0.4.9.dist-info/METADATA
doka-0.4.9.dist-info/RECORD
