Metadata-Version: 2.1
Name: doka
Version: 0.4.9
Summary: 
Author: axxil
Author-email: axxil@yandex.ru
Requires-Python: >=3.6,<4.0
Classifier: Programming Language :: Python :: 3
Classifier: Programming Language :: Python :: 3.6
Classifier: Programming Language :: Python :: 3.7
Requires-Dist: fire (>=0.1.3,<0.2.0)
Requires-Dist: marshmallow (>=2.19,<3.0)
Requires-Dist: python-dotenv (>=0.10.3,<0.11.0)
Requires-Dist: pyyaml (>=5.1,<6.0)
Requires-Dist: requests (>=2.22,<3.0)
Requires-Dist: termcolor (>=1.1,<2.0)
